eve2cml/__init__.py
eve2cml/_version.py
eve2cml/log.py
eve2cml/main.py
eve2cml/mapper.py
eve2cml/eve/__init__.py
eve2cml/eve/config.py
eve2cml/eve/configset.py
eve2cml/eve/decode.py
eve2cml/eve/interface.py
eve2cml/eve/lab.py
eve2cml/eve/network.py
eve2cml/eve/node.py
eve2cml/eve/objects.py
eve2cml/eve/task.py
eve2cml/eve/textobject.py
eve2cml/eve/topology.py
eve2cml/map_data/__init__.py
eve2cml/map_data/default.yaml
eve2cml-0.1.4.dist-info/METADATA
eve2cml-0.1.4.dist-info/WHEEL
eve2cml-0.1.4.dist-info/entry_points.txt
eve2cml-0.1.4.dist-info/licenses/LICENSE
eve2cml-0.1.4.dist-info/RECORD
