Metadata-Version: 2.4
Name: eve2cml
Version: 0.1.4
Summary: A CLI tool to convert EVE-NG XML topology data into CML2 topology data as YAML
Project-URL: Homepage, https://developer.cisco.com/modeling-labs
Project-URL: Repository, https://github.com/ciscodevnet/eve2cml
Project-URL: Issues, https://github.com/ciscodevnet/eve2cml/issues
Project-URL: Changelog, https://github.com/ciscodevnet/eve2cml/blob/master/CHANGELOG.md
Author-email: Ralph Schmieder <rschmied@cisco.com>
License: MIT
License-File: LICENSE
Keywords: automation,network-programming,simulation,tools,virtualization
Classifier: Development Status :: 4 - Beta
Classifier: Environment :: Console
Classifier: Intended Audience :: Telecommunications Industry
Classifier: License :: OSI Approved :: MIT License
Classifier: Operating System :: OS Independent
Classifier: Programming Language :: Python :: 3
Classifier: Programming Language :: Python :: 3.9
Classifier: Programming Language :: Python :: 3.10
Classifier: Programming Language :: Python :: 3.11
Classifier: Programming Language :: Python :: 3.12
Classifier: Topic :: Internet
Requires-Python: >=3.9
Requires-Dist: beautifulsoup4>=4.12.3
Requires-Dist: pyyaml>=6.0.1
